huma_signals/__init__.py
huma_signals/adapters/__init__.py
huma_signals/adapters/ethereum_wallet/README.md
huma_signals/adapters/ethereum_wallet/__init__.py
huma_signals/adapters/ethereum_wallet/adapter.py
huma_signals/adapters/ethereum_wallet/settings.py
huma_signals/adapters/lending_pools/README.md
huma_signals/adapters/lending_pools/__init__.py
huma_signals/adapters/lending_pools/abi/BaseCreditPool.json
huma_signals/adapters/lending_pools/abi/BasePoolConfig.json
huma_signals/adapters/lending_pools/abi/ReceivableFactoringPool.json
huma_signals/adapters/lending_pools/abi/ReceivableFactoringPoolSuperfluid.json
huma_signals/adapters/lending_pools/adapter.py
huma_signals/adapters/lending_pools/registry.py
huma_signals/adapters/lending_pools/settings.py
huma_signals/adapters/models.py
huma_signals/adapters/polygon_wallet/README.md
huma_signals/adapters/polygon_wallet/__init__.py
huma_signals/adapters/polygon_wallet/adapter.py
huma_signals/adapters/polygon_wallet/settings.py
huma_signals/adapters/request_network/README.md
huma_signals/adapters/request_network/__init__.py
huma_signals/adapters/request_network/models.py
huma_signals/adapters/request_network/request_invoice_adapter.py
huma_signals/adapters/request_network/request_transaction_adapter.py
huma_signals/adapters/request_network/settings.py
huma_signals/adapters/superfluid/__init__.py
huma_signals/adapters/superfluid/settings.py
huma_signals/adapters/superfluid/superfluid_adapter.py
huma_signals/adapters/superfluid/superfluid_models.py
huma_signals/clients/__init__.py
huma_signals/clients/eth_client/__init__.py
huma_signals/clients/eth_client/eth_client.py
huma_signals/clients/eth_client/eth_types.py
huma_signals/clients/polygon_client/__init__.py
huma_signals/clients/polygon_client/polygon_client.py
huma_signals/clients/polygon_client/polygon_types.py
huma_signals/clients/request_client/__init__.py
huma_signals/clients/request_client/request_client.py
huma_signals/clients/request_client/request_types.py
huma_signals-0.7.0.dist-info/LICENSE
huma_signals-0.7.0.dist-info/METADATA
huma_signals-0.7.0.dist-info/WHEEL
huma_signals-0.7.0.dist-info/RECORD
