Metadata-Version: 2.1
Name: huma-signals
Version: 0.7.0
Summary: Enables access to high-quality signals about a borrower's income, assets, and liabilities.
Home-page: https://github.com/00labs/huma-signals/
License: AGPL v3
Author: Jiatu Liu
Author-email: jiatu@huma.finance
Requires-Python: >=3.10,<3.11
Classifier: License :: Other/Proprietary License
Classifier: Programming Language :: Python :: 3
Classifier: Programming Language :: Python :: 3.10
Requires-Dist: aiofiles (>=22.1.0,<23.0.0)
Requires-Dist: httpx (>=0.24.0,<0.25.0)
Requires-Dist: huma-utils (>=0.3.0,<0.4.0)
Requires-Dist: orjson (>=3.8.5,<4.0.0)
Requires-Dist: pandas (>=1.5.2,<2.0.0)
Requires-Dist: structlog (>=22.3.0,<23.0.0)
Requires-Dist: urllib3 (>=1.26,<2.0)
Requires-Dist: web3 (>=6.1.0,<7.0.0)
Project-URL: Documentation, https://docs.huma.finance/developer-guidelines/decentralized_signal_portfolio
Project-URL: Repository, https://github.com/00labs/huma-signals.git
